smartheattable/__init__.py
smartheattable/__main__.py
smartheattable/application.py
smartheattable/gui/__init__.py
smartheattable/gui/ui_mainwindow.py
smartheattable-0.0.2.dist-info/LICENSE
smartheattable-0.0.2.dist-info/METADATA
smartheattable-0.0.2.dist-info/WHEEL
smartheattable-0.0.2.dist-info/top_level.txt
smartheattable-0.0.2.dist-info/RECORD
