Metadata-Version: 2.1
Name: smartheattable
Version: 0.0.2
Summary: Smart heat table software in Python
Author-email: "Paul J.M. van Kan" <paul.vankan@han.nl>, Maarten van den Berg <maarten.vandenberg@han.nl>
Project-URL: Homepage, https://github.com/hancse/smartheattable.git
Classifier: Programming Language :: Python :: 3
Classifier: License :: OSI Approved :: GNU General Public License v3 or later (GPLv3+)
Classifier: Operating System :: OS Independent
Requires-Python: >=3.11
License-File: LICENSE
